douyin_tiktok_scraper/X-Bogus.js
douyin_tiktok_scraper/__init__.py
douyin_tiktok_scraper/scraper.py
douyin_tiktok_scraper-1.2.9.dist-info/LICENSE
douyin_tiktok_scraper-1.2.9.dist-info/METADATA
douyin_tiktok_scraper-1.2.9.dist-info/WHEEL
douyin_tiktok_scraper-1.2.9.dist-info/top_level.txt
douyin_tiktok_scraper-1.2.9.dist-info/RECORD
