Metadata-Version: 2.1
Name: douyin-tiktok-scraper
Version: 1.2.9
Summary: Douyin/TikTok async data scraper.
Home-page: https://github.com/Evil0ctal/Douyin_TikTok_Download_API
Author: Evil0ctal
Author-email: Evil0ctal1985@gmail.com
License: MIT License
Keywords: TikTok,Douyin,抖音,Scraper,Crawler,API,Download,Video,No Watermark,Async
Platform: UNKNOWN
Classifier: Programming Language :: Python :: 3
Classifier: Programming Language :: Python :: 3.6
Classifier: Programming Language :: Python :: 3.7
Classifier: Programming Language :: Python :: 3.8
Classifier: Programming Language :: Python :: 3.9
Classifier: Programming Language :: Python :: 3.10
Classifier: Programming Language :: Python :: 3 :: Only
Requires-Python: >=3.6
License-File: LICENSE
